uniseg2/__init__.py
uniseg2/breaking.py
uniseg2/codepoint.py
uniseg2/db.py
uniseg2/db_lookups.py
uniseg2/db_lookups_test.py
uniseg2/graphemecluster.py
uniseg2/graphemeclustertest.py
uniseg2/linebreak.py
uniseg2/linebreaktest.py
uniseg2/sentencebreak.py
uniseg2/sentencebreaktest.py
uniseg2/test.py
uniseg2/wordbreak.py
uniseg2/wordbreaktest.py
uniseg2/wrap.py
uniseg2/wraptest.py
uniseg2-0.8.0.dist-info/LICENSE
uniseg2-0.8.0.dist-info/METADATA
uniseg2-0.8.0.dist-info/WHEEL
uniseg2-0.8.0.dist-info/top_level.txt
uniseg2-0.8.0.dist-info/RECORD
