Metadata-Version: 2.1
Name: uniseg2
Version: 0.8.0
Summary: Determine Unicode text segmentations
Home-page: https://github.com/maxbachmann/uniseg
Author: Max Bachmann
Author-email: pypi@maxbachmann.de
License: MIT
Classifier: Development Status :: 4 - Beta
Classifier: License :: OSI Approved :: MIT License
Classifier: Operating System :: OS Independent
Classifier: Programming Language :: Python :: 3
Classifier: Programming Language :: Python :: 3.6
Classifier: Programming Language :: Python :: 3.7
Classifier: Programming Language :: Python :: 3.8
Classifier: Programming Language :: Python :: 3.9
Classifier: Programming Language :: Python :: 3.10
Classifier: Programming Language :: Python :: 3.11
Classifier: Topic :: Text Processing
Requires-Python: >=3.6
License-File: LICENSE
